transcription_normalization_client.py
transcription_normalization_client-1.0.1.dist-info/METADATA
transcription_normalization_client-1.0.1.dist-info/WHEEL
transcription_normalization_client-1.0.1.dist-info/entry_points.txt
transcription_normalization_client-1.0.1.dist-info/top_level.txt
transcription_normalization_client-1.0.1.dist-info/RECORD
